soapystone/__init__.py
soapystone/checker.py
soapystone/phrases.py
soapystone-0.1.0.dist-info/LICENSE
soapystone-0.1.0.dist-info/WHEEL
soapystone-0.1.0.dist-info/METADATA
soapystone-0.1.0.dist-info/RECORD
